{
  "room_layout": {
    "create_at": "2018-03-07T14:23:08.551981+00:00",
    "labels": [
      {
        "text": "ЗАЛ",
        "x": 32,
        "y": 34
      },
      {
        "text": "HP STAGE 1",
        "x": 32,
        "y": 402
      },
      {
        "text": "HP STAGE 2",
        "x": 247,
        "y": 402
      },
      {
        "text": "VIP ROOM",
        "x": 32,
        "y": 461
      },
      {
        "text": "LG ROOM",
        "x": 247,
        "y": 461
      }
    ],
    "name": "room1",
    "places": [
      {
        "computer": {
          "active": false,
          "created_on": "2018-03-07T14:21:52.922877+00:00",
          "name": "111",
          "public_id": "be2ec473-b59a-442b-ad3f-6cfc15064c9d"
        },
        "computer_pid": "be2ec473-b59a-442b-ad3f-6cfc15064c9d",
        "coors": {
          "angle": -1.5708,
          "id": "0",
          "type": 0,
          "x": 32,
          "y": 70
        },
        "create_at": "2018-03-07T14:27:54.945337+00:00",
        "offer": {
          "cost": 123,
          "create_at": "2018-03-07T14:22:11.867506+00:00",
          "name": "111",
          "public_id": "4a4f3f84-20a9-4ece-ad74-78ef3bc0e92d"
        },
        "offer_pid": "4a4f3f84-20a9-4ece-ad74-78ef3bc0e92d",
        "orders": [
          {
            "access_code": "xmp1mt5uw8",
            "cost": 111,
            "create_at": "2018-03-13T09:31:34.314591+00:00",
            "end_at": "2018-03-13T18:29:27.422880+00:00",
            "place": {
              "computer": {
                "active": false,
                "created_on": "2018-03-07T14:21:52.922877+00:00",
                "name": "111",
                "public_id": "be2ec473-b59a-442b-ad3f-6cfc15064c9d"
              }
            },
            "place_pid": "8bd11aee-2eef-4f18-a3e4-4980876a2397",
            "public_id": "909a8cda-e7ed-4888-a9db-7754593a6cf4",
            "start_at": "2018-03-13T12:59:27.422815+00:00",
            "user_pid": "dd3ebb2b-81b5-4de1-bca4-f6a9aa882788"
          },
          {
            "access_code": "xmp1mt5uw8",
            "cost": 123,
            "create_at": "2018-03-14T15:14:46.447004+00:00",
            "end_at": "2018-03-07T20:05:27.826978+00:00",
            "place": {
              "computer": {
                "active": false,
                "created_on": "2018-03-07T14:21:52.922877+00:00",
                "name": "111",
                "public_id": "be2ec473-b59a-442b-ad3f-6cfc15064c9d"
              }
            },
            "place_pid": "8bd11aee-2eef-4f18-a3e4-4980876a2397",
            "public_id": "b2f4ce85-c000-4369-84be-4cc1203dea2d",
            "start_at": "2018-03-07T20:04:27.826978+00:00",
            "user_pid": "df2ba5d4-9845-4542-8318-657eff1b2d10"
          },
          {
            "access_code": "nbqgpyoc",
            "cost": 111,
            "create_at": "2018-03-20T10:05:40.665926+00:00",
            "end_at": "2018-05-20T15:05:26+00:00",
            "place": {
              "computer": {
                "active": false,
                "created_on": "2018-03-07T14:21:52.922877+00:00",
                "name": "111",
                "public_id": "be2ec473-b59a-442b-ad3f-6cfc15064c9d"
              }
            },
            "place_pid": "8bd11aee-2eef-4f18-a3e4-4980876a2397",
            "public_id": "5a0be6b8-e64b-4b05-a06b-4ae01b178ead",
            "start_at": "2018-05-20T14:05:26+00:00",
            "user_pid": "70a79415-7748-4132-9970-8835eabaf6e0"
          },
          {
            "access_code": "7ctzn3yn",
            "cost": 111,
            "create_at": "2018-03-20T10:08:41.732937+00:00",
            "end_at": "2018-08-20T15:08:36+00:00",
            "place": {
              "computer": {
                "active": false,
                "created_on": "2018-03-07T14:21:52.922877+00:00",
                "name": "111",
                "public_id": "be2ec473-b59a-442b-ad3f-6cfc15064c9d"
              }
            },
            "place_pid": "8bd11aee-2eef-4f18-a3e4-4980876a2397",
            "public_id": "07d00e35-bf3f-445d-9086-f9a5f948a77b",
            "start_at": "2018-08-20T14:08:36+00:00",
            "user_pid": "70a79415-7748-4132-9970-8835eabaf6e0"
          }
        ],
        "public_id": "8bd11aee-2eef-4f18-a3e4-4980876a2397",
        "room_layout_pid": "e24979dd-f72a-43a1-9ea2-20fc2e28942a",
        "status": "free"
      },
      {
        "computer": {
          "active": false,
          "created_on": "2018-03-07T14:21:52.922877+00:00",
          "name": "111",
          "public_id": "be2ec473-b59a-442b-ad3f-6cfc15064c9d"
        },
        "computer_pid": "be2ec473-b59a-442b-ad3f-6cfc15064c9d",
        "coors": {
          "angle": -1.5708,
          "id": "2",
          "type": 0,
          "x": 72,
          "y": 70
        },
        "create_at": "2018-03-07T14:28:11.911299+00:00",
        "offer": {
          "cost": 123,
          "create_at": "2018-03-07T14:22:11.867506+00:00",
          "name": "111",
          "public_id": "4a4f3f84-20a9-4ece-ad74-78ef3bc0e92d"
        },
        "offer_pid": "4a4f3f84-20a9-4ece-ad74-78ef3bc0e92d",
        "orders": [
          {
            "access_code": "xmp1mt5uw8",
            "cost": 123,
            "create_at": "2018-03-14T15:00:05.548068+00:00",
            "end_at": "2018-03-07T20:05:27.826978+00:00",
            "place": {
              "computer": {
                "active": false,
                "created_on": "2018-03-07T14:21:52.922877+00:00",
                "name": "111",
                "public_id": "be2ec473-b59a-442b-ad3f-6cfc15064c9d"
              }
            },
            "place_pid": "c4f315bc-c530-41e6-b0c7-78ed9de36191",
            "public_id": "66f5c7d3-43ce-4d7c-9d6f-ae4a91ec3573",
            "start_at": "2018-03-07T20:04:27.826978+00:00",
            "user_pid": "df2ba5d4-9845-4542-8318-657eff1b2d10"
          }
        ],
        "public_id": "c4f315bc-c530-41e6-b0c7-78ed9de36191",
        "room_layout_pid": "e24979dd-f72a-43a1-9ea2-20fc2e28942a",
        "status": "free"
      },
      {
        "computer": {
          "active": false,
          "created_on": "2018-03-07T14:21:52.922877+00:00",
          "name": "111",
          "public_id": "be2ec473-b59a-442b-ad3f-6cfc15064c9d"
        },
        "computer_pid": "be2ec473-b59a-442b-ad3f-6cfc15064c9d",
        "coors": {
          "angle": -1.5708,
          "id": "4",
          "type": 0,
          "x": 112,
          "y": 70
        },
        "create_at": "2018-03-07T14:28:12.439267+00:00",
        "offer": {
          "cost": 123,
          "create_at": "2018-03-07T14:22:11.867506+00:00",
          "name": "111",
          "public_id": "4a4f3f84-20a9-4ece-ad74-78ef3bc0e92d"
        },
        "offer_pid": "4a4f3f84-20a9-4ece-ad74-78ef3bc0e92d",
        "orders": [],
        "public_id": "94f60c04-7e2d-4a3a-84c1-3a0d4d1a5110",
        "room_layout_pid": "e24979dd-f72a-43a1-9ea2-20fc2e28942a",
        "status": "free"
      },
      {
        "computer": {
          "active": false,
          "created_on": "2018-03-07T14:21:52.922877+00:00",
          "name": "111",
          "public_id": "be2ec473-b59a-442b-ad3f-6cfc15064c9d"
        },
        "computer_pid": "be2ec473-b59a-442b-ad3f-6cfc15064c9d",
        "coors": {
          "angle": 1.5708,
          "id": "6",
          "type": 0,
          "x": 52,
          "y": 100
        },
        "create_at": "2018-03-07T14:28:12.794959+00:00",
        "offer": {
          "cost": 123,
          "create_at": "2018-03-07T14:22:11.867506+00:00",
          "name": "111",
          "public_id": "4a4f3f84-20a9-4ece-ad74-78ef3bc0e92d"
        },
        "offer_pid": "4a4f3f84-20a9-4ece-ad74-78ef3bc0e92d",
        "orders": [
          {
            "access_code": "xmp1mt5uw8",
            "cost": 123,
            "create_at": "2018-03-14T15:50:21.242263+00:00",
            "end_at": "2018-03-07T20:05:27.826978+00:00",
            "place": {
              "computer": {
                "active": false,
                "created_on": "2018-03-07T14:21:52.922877+00:00",
                "name": "111",
                "public_id": "be2ec473-b59a-442b-ad3f-6cfc15064c9d"
              }
            },
            "place_pid": "9eb6f8ea-4fcd-4f13-95d6-677d68ed9d9b",
            "public_id": "4f359fa0-13a6-4d3a-9822-b04d77da23d2",
            "start_at": "2018-03-07T20:04:27.826978+00:00",
            "user_pid": "df2ba5d4-9845-4542-8318-657eff1b2d10"
          },
          {
            "access_code": "xmp1mt5uw8",
            "cost": 123,
            "create_at": "2018-03-14T15:53:15.921424+00:00",
            "end_at": "2018-04-07T20:05:27.826978+00:00",
            "place": {
              "computer": {
                "active": false,
                "created_on": "2018-03-07T14:21:52.922877+00:00",
                "name": "111",
                "public_id": "be2ec473-b59a-442b-ad3f-6cfc15064c9d"
              }
            },
            "place_pid": "9eb6f8ea-4fcd-4f13-95d6-677d68ed9d9b",
            "public_id": "f6c0afe1-f4b9-406c-911a-fc5863dc85a9",
            "start_at": "2018-04-07T20:04:27.826978+00:00",
            "user_pid": "df2ba5d4-9845-4542-8318-657eff1b2d10"
          },
          {
            "access_code": "xmp1mt5uw8",
            "cost": 123,
            "create_at": "2018-03-14T15:55:03.583532+00:00",
            "end_at": "2018-05-07T20:05:27.826978+00:00",
            "place": {
              "computer": {
                "active": false,
                "created_on": "2018-03-07T14:21:52.922877+00:00",
                "name": "111",
                "public_id": "be2ec473-b59a-442b-ad3f-6cfc15064c9d"
              }
            },
            "place_pid": "9eb6f8ea-4fcd-4f13-95d6-677d68ed9d9b",
            "public_id": "5e99e051-4b4c-42d8-a957-a2613a8be170",
            "start_at": "2018-05-07T20:04:27.826978+00:00",
            "user_pid": "df2ba5d4-9845-4542-8318-657eff1b2d10"
          },
          {
            "access_code": "xmp1mt5uw8",
            "cost": 123,
            "create_at": "2018-03-15T11:07:02.681405+00:00",
            "end_at": "2018-08-07T23:05:27.826978+00:00",
            "place": {
              "computer": {
                "active": false,
                "created_on": "2018-03-07T14:21:52.922877+00:00",
                "name": "111",
                "public_id": "be2ec473-b59a-442b-ad3f-6cfc15064c9d"
              }
            },
            "place_pid": "9eb6f8ea-4fcd-4f13-95d6-677d68ed9d9b",
            "public_id": "32e912f9-cbba-4db7-9d9b-f66655ffb652",
            "start_at": "2018-08-07T21:04:27.826978+00:00",
            "user_pid": "df2ba5d4-9845-4542-8318-657eff1b2d10"
          },
          {
            "access_code": "ulozo5z7",
            "cost": 123,
            "create_at": "2018-03-15T12:52:20.525304+00:00",
            "end_at": "2011-08-08T00:05:27.826978+00:00",
            "place": {
              "computer": {
                "active": false,
                "created_on": "2018-03-07T14:21:52.922877+00:00",
                "name": "111",
                "public_id": "be2ec473-b59a-442b-ad3f-6cfc15064c9d"
              }
            },
            "place_pid": "9eb6f8ea-4fcd-4f13-95d6-677d68ed9d9b",
            "public_id": "07a55b0b-8215-4ecb-9ec2-23fa2ab7dcff",
            "start_at": "2011-08-07T22:04:27.826978+00:00",
            "user_pid": "df2ba5d4-9845-4542-8318-657eff1b2d10"
          }
        ],
        "public_id": "9eb6f8ea-4fcd-4f13-95d6-677d68ed9d9b",
        "room_layout_pid": "e24979dd-f72a-43a1-9ea2-20fc2e28942a",
        "status": "free"
      },
      {
        "computer": {
          "active": false,
          "created_on": "2018-03-07T14:21:52.922877+00:00",
          "name": "111",
          "public_id": "be2ec473-b59a-442b-ad3f-6cfc15064c9d"
        },
        "computer_pid": "be2ec473-b59a-442b-ad3f-6cfc15064c9d",
        "coors": {
          "angle": 1.5708,
          "id": "8",
          "type": 0,
          "x": 92,
          "y": 100
        },
        "create_at": "2018-03-07T14:28:13.067480+00:00",
        "offer": {
          "cost": 123,
          "create_at": "2018-03-07T14:22:11.867506+00:00",
          "name": "111",
          "public_id": "4a4f3f84-20a9-4ece-ad74-78ef3bc0e92d"
        },
        "offer_pid": "4a4f3f84-20a9-4ece-ad74-78ef3bc0e92d",
        "orders": [
          {
            "access_code": "xmp1mt5uw8",
            "cost": 123,
            "create_at": "2018-03-14T15:45:17.933264+00:00",
            "end_at": "2018-03-07T20:05:27.826978+00:00",
            "place": {
              "computer": {
                "active": false,
                "created_on": "2018-03-07T14:21:52.922877+00:00",
                "name": "111",
                "public_id": "be2ec473-b59a-442b-ad3f-6cfc15064c9d"
              }
            },
            "place_pid": "8f496170-1436-4a5d-a201-121d1b5d8649",
            "public_id": "7e74e7d3-d4f0-4a8f-a11f-72df7cfc3f92",
            "start_at": "2018-03-07T20:04:27.826978+00:00",
            "user_pid": "df2ba5d4-9845-4542-8318-657eff1b2d10"
          }
        ],
        "public_id": "8f496170-1436-4a5d-a201-121d1b5d8649",
        "room_layout_pid": "e24979dd-f72a-43a1-9ea2-20fc2e28942a",
        "status": "free"
      },
      {
        "computer": {
          "active": false,
          "created_on": "2018-03-07T14:21:52.922877+00:00",
          "name": "111",
          "public_id": "be2ec473-b59a-442b-ad3f-6cfc15064c9d"
        },
        "computer_pid": "be2ec473-b59a-442b-ad3f-6cfc15064c9d",
        "coors": {
          "angle": -1.5708,
          "id": "0",
          "type": 0,
          "x": 247,
          "y": 70
        },
        "create_at": "2018-03-07T14:28:13.318700+00:00",
        "offer": {
          "cost": 123,
          "create_at": "2018-03-07T14:22:11.867506+00:00",
          "name": "111",
          "public_id": "4a4f3f84-20a9-4ece-ad74-78ef3bc0e92d"
        },
        "offer_pid": "4a4f3f84-20a9-4ece-ad74-78ef3bc0e92d",
        "orders": [],
        "public_id": "bdaf9415-2748-474f-8c68-8d033aa745ac",
        "room_layout_pid": "e24979dd-f72a-43a1-9ea2-20fc2e28942a",
        "status": "free"
      }
    ],
    "public_id": "e24979dd-f72a-43a1-9ea2-20fc2e28942a",
    "room_pid": "ef051097-2a06-4cba-9c04-a26900e5c1a4",
    "walls": [
      {
        "end": {
          "x": 344,
          "y": 375
        },
        "start": {
          "x": 32,
          "y": 375
        }
      }
    ]
  }
}
